Directory_Manager/__init__.py
Directory_Manager/directory_manager.py
Directory_Manager/file_manager.py
Directory_Manager/path_manager.py
Directory_Manager/pqt_file_dialog.py
Directory_Manager/ps_file_dialog.py
Directory_Manager/tk_file_dialog.py
Directory_Manager/version.py
Directory_Manager/zipper.py
CD_MD-0.3.0.dist-info/LICENSE.md
CD_MD-0.3.0.dist-info/LICENSE.txt
CD_MD-0.3.0.dist-info/METADATA
CD_MD-0.3.0.dist-info/WHEEL
CD_MD-0.3.0.dist-info/top_level.txt
CD_MD-0.3.0.dist-info/RECORD
