Metadata-Version: 2.1
Name: CD-MD
Version: 0.3.0
Summary: A package containing utilities for file and directory management, ZIP operations, and more.
Home-page: https://codedocta.com
Author: codedocta
Author-email: codedocta@gmail.com
Project-URL: Bug Reports, https://github.com/codedocta/CD_MD/issues
Project-URL: Source, https://github.com/codedocta/CD_MD/
Keywords: file management,directory management,zip operations
Classifier: Development Status :: 4 - Beta
Classifier: Intended Audience :: Developers
Classifier: License :: OSI Approved :: MIT License
Classifier: Programming Language :: Python :: 3.11
License-File: LICENSE.md
License-File: LICENSE.txt
Requires-Dist: pyside6 ==6.5.3
Requires-Dist: pyqt6 ==6.5.2
